m/cli/__init__.py
m/cli/load.py
m/cli/main.py
m/commands/alias.py
m/commands/config.py
m/commands/version.py
m/config/load.py
m/config/types.py
m/utils/cmd.py
m/utils/console.py
m/utils/helpers.py
m/utils/inject.py
m/utils/merge.py
m/utils/path.py
m/utils/register.py
m/version.py
muspi_merol-0.2.5.dist-info/METADATA
muspi_merol-0.2.5.dist-info/WHEEL
muspi_merol-0.2.5.dist-info/entry_points.txt
muspi_merol-0.2.5.dist-info/RECORD
