Metadata-Version: 2.1
Name: muspi-merol
Version: 0.2.5
Summary: CLI utilities for personal use
Requires-Python: >=3.12
Requires-Dist: rich<15,>=13.9
Requires-Dist: typer-slim<0.21.0,>=0.16.1
Provides-Extra: all
Requires-Dist: mm-chat; extra == "all"
Requires-Dist: mm-read; extra == "all"
